miltertest/__init__.py
miltertest/client.py
miltertest/codec.py
miltertest/constants.py
miltertest-1.0.0.dist-info/METADATA
miltertest-1.0.0.dist-info/WHEEL
miltertest-1.0.0.dist-info/licenses/COPYING
miltertest-1.0.0.dist-info/RECORD
