Metadata-Version: 2.3
Name: miltertest
Version: 1.0.0
Summary: Pure Python implementation of the milter protocol
Project-URL: Homepage, https://github.com/flowerysong/miltertest
Author-email: Paul Arthur <paul.arthur@flowerysong.com>
License-File: COPYING
Classifier: License :: OSI Approved :: GNU General Public License v3 (GPLv3)
Classifier: Operating System :: OS Independent
Classifier: Programming Language :: Python :: 3
Requires-Python: >=3.8
